<annotation>
  <folder>croatia</folder>
  <filename>Sequenza 012473.png</filename>
  <segmented>0</segmented>
  <size>
    <width>1280</width>
    <height>720</height>
    <depth>3</depth>
  </size>
  <object>
    <name>croatia_player</name>
    <pose>Unspecified</pose>
    <truncated>0</truncated>
    <difficult>0</difficult>
    <bndbox>
      <xmin>857</xmin>
      <ymin>496</ymin>
      <xmax>942</xmax>
      <ymax>665</ymax>
    </bndbox>
  </object>
  <object>
    <name>croatia_player</name>
    <pose>Unspecified</pose>
    <truncated>0</truncated>
    <difficult>0</difficult>
    <bndbox>
      <xmin>956</xmin>
      <ymin>460</ymin>
      <xmax>1035</xmax>
      <ymax>598</ymax>
    </bndbox>
  </object>
  <object>
    <name>croatia_player</name>
    <pose>Unspecified</pose>
    <truncated>0</truncated>
    <difficult>0</difficult>
    <bndbox>
      <xmin>1025</xmin>
      <ymin>317</ymin>
      <xmax>1126</xmax>
      <ymax>442</ymax>
    </bndbox>
  </object>
</annotation>
