<annotation>
  <folder>croatia</folder>
  <filename>Sequenza 010979.png</filename>
  <segmented>0</segmented>
  <size>
    <width>1280</width>
    <height>720</height>
    <depth>3</depth>
  </size>
  <object>
    <name>croatia_player</name>
    <pose>Unspecified</pose>
    <truncated>0</truncated>
    <difficult>0</difficult>
    <bndbox>
      <xmin>97</xmin>
      <ymin>195</ymin>
      <xmax>144</xmax>
      <ymax>279</ymax>
    </bndbox>
  </object>
  <object>
    <name>croatia_player</name>
    <pose>Unspecified</pose>
    <truncated>0</truncated>
    <difficult>0</difficult>
    <bndbox>
      <xmin>205</xmin>
      <ymin>254</ymin>
      <xmax>250</xmax>
      <ymax>335</ymax>
    </bndbox>
  </object>
  <object>
    <name>croatia_player</name>
    <pose>Unspecified</pose>
    <truncated>0</truncated>
    <difficult>0</difficult>
    <bndbox>
      <xmin>757</xmin>
      <ymin>266</ymin>
      <xmax>795</xmax>
      <ymax>341</ymax>
    </bndbox>
  </object>
</annotation>
